[
  {
    "end": "Bava Batra 2a:5",
    "length": 5,
    "start": "Bava Batra 2a:1"
  },
  {
    "end": "Bava Batra 2b:4",
    "length": 5,
    "start": "Bava Batra 2a:6"
  },
  {
    "end": "Bava Batra 2b:6",
    "length": 2,
    "start": "Bava Batra 2b:5"
  },
  {
    "end": "Bava Batra 3a:1",
    "length": 12,
    "start": "Bava Batra 2b:7"
  },
  {
    "end": "Bava Batra 3a:14",
    "length": 13,
    "start": "Bava Batra 3a:2"
  },
  {
    "end": "Bava Batra 3a:21",
    "length": 7,
    "start": "Bava Batra 3a:15"
  },
  {
    "end": "Bava Batra 3b:3",
    "length": 6,
    "start": "Bava Batra 3a:22"
  },
  {
    "end": "Bava Batra 3b:7",
    "length": 4,
    "start": "Bava Batra 3b:4"
  },
  {
    "end": "Bava Batra 3b:13",
    "length": 6,
    "start": "Bava Batra 3b:8"
  },
  {
    "end": "Bava Batra 4a:9",
    "length": 12,
    "start": "Bava Batra 3b:14"
  },
  {
    "end": "Bava Batra 4a:10",
    "length": 1,
    "start": "Bava Batra 4a:10"
  },
  {
    "end": "Bava Batra 4a:11",
    "length": 1,
    "start": "Bava Batra 4a:11"
  },
  {
    "end": "Bava Batra 4a:14",
    "length": 3,
    "start": "Bava Batra 4a:12"
  },
  {
    "end": "Bava Batra 4b:3",
    "length": 6,
    "start": "Bava Batra 4a:15"
  },
  {
    "end": "Bava Batra 4b:6",
    "length": 3,
    "start": "Bava Batra 4b:4"
  },
  {
    "end": "Bava Batra 4b:7",
    "length": 1,
    "start": "Bava Batra 4b:7"
  },
  {
    "end": "Bava Batra 5a:4",
    "length": 14,
    "start": "Bava Batra 4b:8"
  },
  {
    "end": "Bava Batra 5a:6",
    "length": 2,
    "start": "Bava Batra 5a:5"
  },
  {
    "end": "Bava Batra 5b:6",
    "length": 7,
    "start": "Bava Batra 5a:7"
  },
  {
    "end": "Bava Batra 6a:6",
    "length": 7,
    "start": "Bava Batra 5b:7"
  },
  {
    "end": "Bava Batra 6a:8",
    "length": 2,
    "start": "Bava Batra 6a:7"
  },
  {
    "end": "Bava Batra 6a:9",
    "length": 1,
    "start": "Bava Batra 6a:9"
  },
  {
    "end": "Bava Batra 6b:1",
    "length": 6,
    "start": "Bava Batra 6a:10"
  },
  {
    "end": "Bava Batra 6b:2",
    "length": 1,
    "start": "Bava Batra 6b:2"
  },
  {
    "end": "Bava Batra 6b:12",
    "length": 10,
    "start": "Bava Batra 6b:3"
  },
  {
    "end": "Bava Batra 7b:5",
    "length": 20,
    "start": "Bava Batra 6b:13"
  },
  {
    "end": "Bava Batra 7b:7",
    "length": 2,
    "start": "Bava Batra 7b:6"
  },
  {
    "end": "Bava Batra 7b:9",
    "length": 2,
    "start": "Bava Batra 7b:8"
  },
  {
    "end": "Bava Batra 7b:10",
    "length": 1,
    "start": "Bava Batra 7b:10"
  },
  {
    "end": "Bava Batra 7b:13",
    "length": 3,
    "start": "Bava Batra 7b:11"
  },
  {
    "end": "Bava Batra 8a:11",
    "length": 14,
    "start": "Bava Batra 7b:14"
  },
  {
    "end": "Bava Batra 8b:4",
    "length": 11,
    "start": "Bava Batra 8a:12"
  },
  {
    "end": "Bava Batra 9a:3",
    "length": 17,
    "start": "Bava Batra 8b:5"
  },
  {
    "end": "Bava Batra 10a:1",
    "length": 25,
    "start": "Bava Batra 9a:4"
  },
  {
    "end": "Bava Batra 11a:1",
    "length": 30,
    "start": "Bava Batra 10a:2"
  },
  {
    "end": "Bava Batra 11a:4",
    "length": 3,
    "start": "Bava Batra 11a:2"
  },
  {
    "end": "Bava Batra 11a:6",
    "length": 2,
    "start": "Bava Batra 11a:5"
  },
  {
    "end": "Bava Batra 11a:9",
    "length": 3,
    "start": "Bava Batra 11a:7"
  },
  {
    "end": "Bava Batra 11b:4",
    "length": 9,
    "start": "Bava Batra 11a:10"
  },
  {
    "end": "Bava Batra 12a:6",
    "length": 14,
    "start": "Bava Batra 11b:5"
  },
  {
    "end": "Bava Batra 12a:12",
    "length": 6,
    "start": "Bava Batra 12a:7"
  },
  {
    "end": "Bava Batra 12b:8",
    "length": 11,
    "start": "Bava Batra 12a:13"
  },
  {
    "end": "Bava Batra 13a:1",
    "length": 7,
    "start": "Bava Batra 12b:9"
  },
  {
    "end": "Bava Batra 13b:8",
    "length": 14,
    "start": "Bava Batra 13a:2"
  },
  {
    "end": "Bava Batra 14a:4",
    "length": 8,
    "start": "Bava Batra 13b:9"
  },
  {
    "end": "Bava Batra 14b:7",
    "length": 18,
    "start": "Bava Batra 14a:5"
  },
  {
    "end": "Bava Batra 15b:11",
    "length": 33,
    "start": "Bava Batra 14b:8"
  },
  {
    "end": "Bava Batra 17a:7",
    "length": 52,
    "start": "Bava Batra 15b:12"
  },
  {
    "end": "Bava Batra 17a:10",
    "length": 3,
    "start": "Bava Batra 17a:8"
  },
  {
    "end": "Bava Batra 17b:3",
    "length": 3,
    "start": "Bava Batra 17b:1"
  },
  {
    "end": "Bava Batra 19a:1",
    "length": 38,
    "start": "Bava Batra 17b:4"
  },
  {
    "end": "Bava Batra 19a:3",
    "length": 2,
    "start": "Bava Batra 19a:2"
  },
  {
    "end": "Bava Batra 19a:8",
    "length": 5,
    "start": "Bava Batra 19a:4"
  },
  {
    "end": "Bava Batra 19a:16",
    "length": 8,
    "start": "Bava Batra 19a:9"
  },
  {
    "end": "Bava Batra 19b:2",
    "length": 5,
    "start": "Bava Batra 19a:17"
  },
  {
    "end": "Bava Batra 19b:6",
    "length": 4,
    "start": "Bava Batra 19b:3"
  },
  {
    "end": "Bava Batra 20b:5",
    "length": 26,
    "start": "Bava Batra 19b:7"
  },
  {
    "end": "Bava Batra 20b:6",
    "length": 1,
    "start": "Bava Batra 20b:6"
  },
  {
    "end": "Bava Batra 20b:7",
    "length": 1,
    "start": "Bava Batra 20b:7"
  },
  {
    "end": "Bava Batra 20b:10",
    "length": 3,
    "start": "Bava Batra 20b:8"
  },
  {
    "end": "Bava Batra 20b:11",
    "length": 1,
    "start": "Bava Batra 20b:11"
  },
  {
    "end": "Bava Batra 20b:13",
    "length": 2,
    "start": "Bava Batra 20b:12"
  },
  {
    "end": "Bava Batra 20b:14",
    "length": 1,
    "start": "Bava Batra 20b:14"
  },
  {
    "end": "Bava Batra 20b:15",
    "length": 1,
    "start": "Bava Batra 20b:15"
  },
  {
    "end": "Bava Batra 21a:8",
    "length": 9,
    "start": "Bava Batra 20b:16"
  },
  {
    "end": "Bava Batra 21b:3",
    "length": 8,
    "start": "Bava Batra 21a:9"
  },
  {
    "end": "Bava Batra 22a:5",
    "length": 14,
    "start": "Bava Batra 21b:4"
  },
  {
    "end": "Bava Batra 22a:12",
    "length": 7,
    "start": "Bava Batra 22a:6"
  },
  {
    "end": "Bava Batra 22a:13",
    "length": 1,
    "start": "Bava Batra 22a:13"
  },
  {
    "end": "Bava Batra 22b:9",
    "length": 10,
    "start": "Bava Batra 22a:14"
  },
  {
    "end": "Bava Batra 22b:10",
    "length": 1,
    "start": "Bava Batra 22b:10"
  },
  {
    "end": "Bava Batra 23a:2",
    "length": 5,
    "start": "Bava Batra 22b:11"
  },
  {
    "end": "Bava Batra 23a:3",
    "length": 1,
    "start": "Bava Batra 23a:3"
  },
  {
    "end": "Bava Batra 23a:6",
    "length": 3,
    "start": "Bava Batra 23a:4"
  },
  {
    "end": "Bava Batra 23a:11",
    "length": 5,
    "start": "Bava Batra 23a:7"
  },
  {
    "end": "Bava Batra 23b:1",
    "length": 1,
    "start": "Bava Batra 23b:1"
  },
  {
    "end": "Bava Batra 24b:1",
    "length": 22,
    "start": "Bava Batra 23b:2"
  },
  {
    "end": "Bava Batra 24b:2",
    "length": 1,
    "start": "Bava Batra 24b:2"
  },
  {
    "end": "Bava Batra 24b:7",
    "length": 5,
    "start": "Bava Batra 24b:3"
  },
  {
    "end": "Bava Batra 24b:11",
    "length": 4,
    "start": "Bava Batra 24b:8"
  },
  {
    "end": "Bava Batra 24b:13",
    "length": 2,
    "start": "Bava Batra 24b:12"
  },
  {
    "end": "Bava Batra 24b:14",
    "length": 1,
    "start": "Bava Batra 24b:14"
  },
  {
    "end": "Bava Batra 25a:1",
    "length": 6,
    "start": "Bava Batra 24b:15"
  },
  {
    "end": "Bava Batra 25a:2",
    "length": 1,
    "start": "Bava Batra 25a:2"
  },
  {
    "end": "Bava Batra 25a:4",
    "length": 2,
    "start": "Bava Batra 25a:3"
  },
  {
    "end": "Bava Batra 25a:11",
    "length": 7,
    "start": "Bava Batra 25a:5"
  },
  {
    "end": "Bava Batra 25b:9",
    "length": 13,
    "start": "Bava Batra 25a:12"
  },
  {
    "end": "Bava Batra 25b:10",
    "length": 1,
    "start": "Bava Batra 25b:10"
  },
  {
    "end": "Bava Batra 25b:11",
    "length": 1,
    "start": "Bava Batra 25b:11"
  },
  {
    "end": "Bava Batra 25b:12",
    "length": 1,
    "start": "Bava Batra 25b:12"
  },
  {
    "end": "Bava Batra 26a:4",
    "length": 7,
    "start": "Bava Batra 25b:13"
  },
  {
    "end": "Bava Batra 26a:6",
    "length": 2,
    "start": "Bava Batra 26a:5"
  },
  {
    "end": "Bava Batra 26a:11",
    "length": 5,
    "start": "Bava Batra 26a:7"
  },
  {
    "end": "Bava Batra 26b:1",
    "length": 3,
    "start": "Bava Batra 26a:12"
  },
  {
    "end": "Bava Batra 26b:7",
    "length": 6,
    "start": "Bava Batra 26b:2"
  },
  {
    "end": "Bava Batra 27b:11",
    "length": 22,
    "start": "Bava Batra 26b:8"
  },
  {
    "end": "Bava Batra 27b:12",
    "length": 1,
    "start": "Bava Batra 27b:12"
  },
  {
    "end": "Bava Batra 27b:15",
    "length": 3,
    "start": "Bava Batra 27b:13"
  },
  {
    "end": "Bava Batra 27b:16",
    "length": 1,
    "start": "Bava Batra 27b:16"
  },
  {
    "end": "Bava Batra 27b:19",
    "length": 3,
    "start": "Bava Batra 27b:17"
  },
  {
    "end": "Bava Batra 27b:21",
    "length": 2,
    "start": "Bava Batra 27b:20"
  },
  {
    "end": "Bava Batra 27b:24",
    "length": 3,
    "start": "Bava Batra 27b:22"
  },
  {
    "end": "Bava Batra 28a:5",
    "length": 5,
    "start": "Bava Batra 28a:1"
  },
  {
    "end": "Bava Batra 29a:8",
    "length": 24,
    "start": "Bava Batra 28a:6"
  },
  {
    "end": "Bava Batra 29b:5",
    "length": 15,
    "start": "Bava Batra 29a:9"
  },
  {
    "end": "Bava Batra 29b:8",
    "length": 3,
    "start": "Bava Batra 29b:6"
  },
  {
    "end": "Bava Batra 32a:6",
    "length": 45,
    "start": "Bava Batra 29b:9"
  },
  {
    "end": "Bava Batra 33b:1",
    "length": 16,
    "start": "Bava Batra 32a:7"
  },
  {
    "end": "Bava Batra 34a:4",
    "length": 11,
    "start": "Bava Batra 33b:2"
  },
  {
    "end": "Bava Batra 35b:3",
    "length": 9,
    "start": "Bava Batra 34b:1"
  },
  {
    "end": "Bava Batra 35b:6",
    "length": 3,
    "start": "Bava Batra 35b:4"
  },
  {
    "end": "Bava Batra 36a:8",
    "length": 9,
    "start": "Bava Batra 35b:7"
  },
  {
    "end": "Bava Batra 36a:12",
    "length": 4,
    "start": "Bava Batra 36a:9"
  },
  {
    "end": "Bava Batra 36b:7",
    "length": 9,
    "start": "Bava Batra 36a:13"
  },
  {
    "end": "Bava Batra 37a:2",
    "length": 3,
    "start": "Bava Batra 36b:8"
  },
  {
    "end": "Bava Batra 37b:4",
    "length": 7,
    "start": "Bava Batra 37a:3"
  },
  {
    "end": "Bava Batra 38a:3",
    "length": 6,
    "start": "Bava Batra 37b:5"
  },
  {
    "end": "Bava Batra 38a:4",
    "length": 1,
    "start": "Bava Batra 38a:4"
  },
  {
    "end": "Bava Batra 38b:1",
    "length": 4,
    "start": "Bava Batra 38a:5"
  },
  {
    "end": "Bava Batra 38b:7",
    "length": 6,
    "start": "Bava Batra 38b:2"
  },
  {
    "end": "Bava Batra 39a:4",
    "length": 5,
    "start": "Bava Batra 38b:8"
  },
  {
    "end": "Bava Batra 39a:6",
    "length": 2,
    "start": "Bava Batra 39a:5"
  },
  {
    "end": "Bava Batra 39b:3",
    "length": 5,
    "start": "Bava Batra 39a:7"
  },
  {
    "end": "Bava Batra 39b:5",
    "length": 2,
    "start": "Bava Batra 39b:4"
  },
  {
    "end": "Bava Batra 40a:5",
    "length": 7,
    "start": "Bava Batra 39b:6"
  },
  {
    "end": "Bava Batra 40b:3",
    "length": 4,
    "start": "Bava Batra 40a:6"
  },
  {
    "end": "Bava Batra 41a:1",
    "length": 6,
    "start": "Bava Batra 40b:4"
  },
  {
    "end": "Bava Batra 41a:3",
    "length": 2,
    "start": "Bava Batra 41a:2"
  },
  {
    "end": "Bava Batra 41a:5",
    "length": 2,
    "start": "Bava Batra 41a:4"
  },
  {
    "end": "Bava Batra 41b:4",
    "length": 9,
    "start": "Bava Batra 41a:6"
  },
  {
    "end": "Bava Batra 41b:9",
    "length": 5,
    "start": "Bava Batra 41b:5"
  },
  {
    "end": "Bava Batra 42a:7",
    "length": 9,
    "start": "Bava Batra 41b:10"
  },
  {
    "end": "Bava Batra 42a:9",
    "length": 2,
    "start": "Bava Batra 42a:8"
  },
  {
    "end": "Bava Batra 42b:4",
    "length": 4,
    "start": "Bava Batra 42b:1"
  },
  {
    "end": "Bava Batra 43a:13",
    "length": 16,
    "start": "Bava Batra 42b:5"
  },
  {
    "end": "Bava Batra 43b:1",
    "length": 2,
    "start": "Bava Batra 43a:14"
  },
  {
    "end": "Bava Batra 44b:10",
    "length": 23,
    "start": "Bava Batra 43b:2"
  },
  {
    "end": "Bava Batra 45a:3",
    "length": 4,
    "start": "Bava Batra 44b:11"
  },
  {
    "end": "Bava Batra 45a:6",
    "length": 3,
    "start": "Bava Batra 45a:4"
  },
  {
    "end": "Bava Batra 46a:4",
    "length": 16,
    "start": "Bava Batra 45a:7"
  },
  {
    "end": "Bava Batra 46a:7",
    "length": 3,
    "start": "Bava Batra 46a:5"
  },
  {
    "end": "Bava Batra 46b:2",
    "length": 4,
    "start": "Bava Batra 46a:8"
  },
  {
    "end": "Bava Batra 46b:7",
    "length": 5,
    "start": "Bava Batra 46b:3"
  },
  {
    "end": "Bava Batra 47a:1",
    "length": 4,
    "start": "Bava Batra 46b:8"
  },
  {
    "end": "Bava Batra 47a:6",
    "length": 5,
    "start": "Bava Batra 47a:2"
  },
  {
    "end": "Bava Batra 47b:1",
    "length": 3,
    "start": "Bava Batra 47a:7"
  },
  {
    "end": "Bava Batra 47b:6",
    "length": 5,
    "start": "Bava Batra 47b:2"
  },
  {
    "end": "Bava Batra 48b:6",
    "length": 17,
    "start": "Bava Batra 47b:7"
  },
  {
    "end": "Bava Batra 49a:4",
    "length": 7,
    "start": "Bava Batra 48b:7"
  },
  {
    "end": "Bava Batra 49b:2",
    "length": 6,
    "start": "Bava Batra 49a:5"
  },
  {
    "end": "Bava Batra 50b:3",
    "length": 17,
    "start": "Bava Batra 49b:3"
  },
  {
    "end": "Bava Batra 51a:1",
    "length": 8,
    "start": "Bava Batra 50b:4"
  },
  {
    "end": "Bava Batra 51b:7",
    "length": 18,
    "start": "Bava Batra 51a:2"
  },
  {
    "end": "Bava Batra 52a:5",
    "length": 6,
    "start": "Bava Batra 51b:8"
  },
  {
    "end": "Bava Batra 52a:7",
    "length": 2,
    "start": "Bava Batra 52a:6"
  },
  {
    "end": "Bava Batra 52b:6",
    "length": 8,
    "start": "Bava Batra 52a:8"
  },
  {
    "end": "Bava Batra 53a:2",
    "length": 6,
    "start": "Bava Batra 52b:7"
  },
  {
    "end": "Bava Batra 53a:7",
    "length": 5,
    "start": "Bava Batra 53a:3"
  },
  {
    "end": "Bava Batra 53b:5",
    "length": 6,
    "start": "Bava Batra 53a:8"
  },
  {
    "end": "Bava Batra 54a:7",
    "length": 12,
    "start": "Bava Batra 53b:6"
  },
  {
    "end": "Bava Batra 54b:1",
    "length": 2,
    "start": "Bava Batra 54a:8"
  },
  {
    "end": "Bava Batra 55a:2",
    "length": 6,
    "start": "Bava Batra 54b:2"
  },
  {
    "end": "Bava Batra 55a:8",
    "length": 6,
    "start": "Bava Batra 55a:3"
  },
  {
    "end": "Bava Batra 56a:9",
    "length": 17,
    "start": "Bava Batra 55a:9"
  },
  {
    "end": "Bava Batra 56b:2",
    "length": 3,
    "start": "Bava Batra 56a:10"
  },
  {
    "end": "Bava Batra 56b:6",
    "length": 4,
    "start": "Bava Batra 56b:3"
  },
  {
    "end": "Bava Batra 56b:8",
    "length": 2,
    "start": "Bava Batra 56b:7"
  },
  {
    "end": "Bava Batra 57a:3",
    "length": 4,
    "start": "Bava Batra 56b:9"
  },
  {
    "end": "Bava Batra 57a:4",
    "length": 1,
    "start": "Bava Batra 57a:4"
  },
  {
    "end": "Bava Batra 57b:8",
    "length": 12,
    "start": "Bava Batra 57a:5"
  },
  {
    "end": "Bava Batra 58a:2",
    "length": 7,
    "start": "Bava Batra 57b:9"
  },
  {
    "end": "Bava Batra 58a:8",
    "length": 6,
    "start": "Bava Batra 58a:3"
  },
  {
    "end": "Bava Batra 58b:3",
    "length": 9,
    "start": "Bava Batra 58a:9"
  },
  {
    "end": "Bava Batra 58b:6",
    "length": 3,
    "start": "Bava Batra 58b:4"
  },
  {
    "end": "Bava Batra 59a:5",
    "length": 8,
    "start": "Bava Batra 58b:7"
  },
  {
    "end": "Bava Batra 59a:6",
    "length": 1,
    "start": "Bava Batra 59a:6"
  },
  {
    "end": "Bava Batra 59a:11",
    "length": 5,
    "start": "Bava Batra 59a:7"
  },
  {
    "end": "Bava Batra 59b:1",
    "length": 2,
    "start": "Bava Batra 59a:12"
  },
  {
    "end": "Bava Batra 59b:2",
    "length": 1,
    "start": "Bava Batra 59b:2"
  },
  {
    "end": "Bava Batra 59b:6",
    "length": 4,
    "start": "Bava Batra 59b:3"
  },
  {
    "end": "Bava Batra 59b:7",
    "length": 1,
    "start": "Bava Batra 59b:7"
  },
  {
    "end": "Bava Batra 60a:1",
    "length": 5,
    "start": "Bava Batra 59b:8"
  },
  {
    "end": "Bava Batra 60a:3",
    "length": 2,
    "start": "Bava Batra 60a:2"
  },
  {
    "end": "Bava Batra 60a:4",
    "length": 1,
    "start": "Bava Batra 60a:4"
  },
  {
    "end": "Bava Batra 60a:5",
    "length": 1,
    "start": "Bava Batra 60a:5"
  },
  {
    "end": "Bava Batra 60a:6",
    "length": 1,
    "start": "Bava Batra 60a:6"
  },
  {
    "end": "Bava Batra 60a:7",
    "length": 1,
    "start": "Bava Batra 60a:7"
  },
  {
    "end": "Bava Batra 60a:8",
    "length": 1,
    "start": "Bava Batra 60a:8"
  },
  {
    "end": "Bava Batra 60a:9",
    "length": 1,
    "start": "Bava Batra 60a:9"
  },
  {
    "end": "Bava Batra 60a:10",
    "length": 1,
    "start": "Bava Batra 60a:10"
  },
  {
    "end": "Bava Batra 60b:3",
    "length": 6,
    "start": "Bava Batra 60a:11"
  },
  {
    "end": "Bava Batra 60b:6",
    "length": 3,
    "start": "Bava Batra 60b:4"
  },
  {
    "end": "Bava Batra 60b:9",
    "length": 3,
    "start": "Bava Batra 60b:7"
  },
  {
    "end": "Bava Batra 60b:10",
    "length": 1,
    "start": "Bava Batra 60b:10"
  },
  {
    "end": "Bava Batra 60b:22",
    "length": 12,
    "start": "Bava Batra 60b:11"
  },
  {
    "end": "Bava Batra 61a:1",
    "length": 1,
    "start": "Bava Batra 61a:1"
  },
  {
    "end": "Bava Batra 61a:3",
    "length": 2,
    "start": "Bava Batra 61a:2"
  },
  {
    "end": "Bava Batra 61a:6",
    "length": 3,
    "start": "Bava Batra 61a:4"
  },
  {
    "end": "Bava Batra 62a:1",
    "length": 14,
    "start": "Bava Batra 61a:7"
  },
  {
    "end": "Bava Batra 62b:1",
    "length": 6,
    "start": "Bava Batra 62a:2"
  },
  {
    "end": "Bava Batra 62b:9",
    "length": 8,
    "start": "Bava Batra 62b:2"
  },
  {
    "end": "Bava Batra 63a:1",
    "length": 5,
    "start": "Bava Batra 62b:10"
  },
  {
    "end": "Bava Batra 63a:3",
    "length": 2,
    "start": "Bava Batra 63a:2"
  },
  {
    "end": "Bava Batra 63b:2",
    "length": 6,
    "start": "Bava Batra 63a:4"
  },
  {
    "end": "Bava Batra 64a:3",
    "length": 7,
    "start": "Bava Batra 63b:3"
  },
  {
    "end": "Bava Batra 64a:6",
    "length": 3,
    "start": "Bava Batra 64a:4"
  },
  {
    "end": "Bava Batra 64a:7",
    "length": 1,
    "start": "Bava Batra 64a:7"
  },
  {
    "end": "Bava Batra 65a:7",
    "length": 19,
    "start": "Bava Batra 64a:8"
  },
  {
    "end": "Bava Batra 65a:10",
    "length": 3,
    "start": "Bava Batra 65a:8"
  },
  {
    "end": "Bava Batra 65b:1",
    "length": 2,
    "start": "Bava Batra 65a:11"
  },
  {
    "end": "Bava Batra 65b:5",
    "length": 4,
    "start": "Bava Batra 65b:2"
  },
  {
    "end": "Bava Batra 66b:5",
    "length": 16,
    "start": "Bava Batra 65b:6"
  },
  {
    "end": "Bava Batra 67a:1",
    "length": 2,
    "start": "Bava Batra 66b:6"
  },
  {
    "end": "Bava Batra 67a:2",
    "length": 1,
    "start": "Bava Batra 67a:2"
  },
  {
    "end": "Bava Batra 67a:4",
    "length": 2,
    "start": "Bava Batra 67a:3"
  },
  {
    "end": "Bava Batra 67a:6",
    "length": 2,
    "start": "Bava Batra 67a:5"
  },
  {
    "end": "Bava Batra 67b:1",
    "length": 4,
    "start": "Bava Batra 67a:7"
  },
  {
    "end": "Bava Batra 67b:2",
    "length": 1,
    "start": "Bava Batra 67b:2"
  },
  {
    "end": "Bava Batra 67b:5",
    "length": 3,
    "start": "Bava Batra 67b:3"
  },
  {
    "end": "Bava Batra 67b:6",
    "length": 1,
    "start": "Bava Batra 67b:6"
  },
  {
    "end": "Bava Batra 68a:3",
    "length": 4,
    "start": "Bava Batra 67b:7"
  },
  {
    "end": "Bava Batra 68a:4",
    "length": 1,
    "start": "Bava Batra 68a:4"
  },
  {
    "end": "Bava Batra 68a:6",
    "length": 2,
    "start": "Bava Batra 68a:5"
  },
  {
    "end": "Bava Batra 68b:6",
    "length": 10,
    "start": "Bava Batra 68a:7"
  },
  {
    "end": "Bava Batra 68b:8",
    "length": 2,
    "start": "Bava Batra 68b:7"
  },
  {
    "end": "Bava Batra 68b:10",
    "length": 2,
    "start": "Bava Batra 68b:9"
  },
  {
    "end": "Bava Batra 69a:3",
    "length": 3,
    "start": "Bava Batra 69a:1"
  },
  {
    "end": "Bava Batra 69a:6",
    "length": 3,
    "start": "Bava Batra 69a:4"
  },
  {
    "end": "Bava Batra 69a:11",
    "length": 5,
    "start": "Bava Batra 69a:7"
  },
  {
    "end": "Bava Batra 69a:14",
    "length": 3,
    "start": "Bava Batra 69a:12"
  },
  {
    "end": "Bava Batra 69b:1",
    "length": 2,
    "start": "Bava Batra 69a:15"
  },
  {
    "end": "Bava Batra 70a:1",
    "length": 7,
    "start": "Bava Batra 69b:2"
  },
  {
    "end": "Bava Batra 70a:7",
    "length": 6,
    "start": "Bava Batra 70a:2"
  },
  {
    "end": "Bava Batra 71a:1",
    "length": 11,
    "start": "Bava Batra 70a:8"
  },
  {
    "end": "Bava Batra 71a:5",
    "length": 4,
    "start": "Bava Batra 71a:2"
  },
  {
    "end": "Bava Batra 71a:9",
    "length": 4,
    "start": "Bava Batra 71a:6"
  },
  {
    "end": "Bava Batra 72b:9",
    "length": 19,
    "start": "Bava Batra 71a:10"
  },
  {
    "end": "Bava Batra 72b:12",
    "length": 3,
    "start": "Bava Batra 72b:10"
  },
  {
    "end": "Bava Batra 73a:2",
    "length": 3,
    "start": "Bava Batra 72b:13"
  },
  {
    "end": "Bava Batra 73a:3",
    "length": 1,
    "start": "Bava Batra 73a:3"
  },
  {
    "end": "Bava Batra 73a:5",
    "length": 2,
    "start": "Bava Batra 73a:4"
  },
  {
    "end": "Bava Batra 73a:7",
    "length": 2,
    "start": "Bava Batra 73a:6"
  },
  {
    "end": "Bava Batra 73a:8",
    "length": 1,
    "start": "Bava Batra 73a:8"
  },
  {
    "end": "Bava Batra 73a:10",
    "length": 2,
    "start": "Bava Batra 73a:9"
  },
  {
    "end": "Bava Batra 73b:1",
    "length": 2,
    "start": "Bava Batra 73a:11"
  },
  {
    "end": "Bava Batra 73b:2",
    "length": 1,
    "start": "Bava Batra 73b:2"
  },
  {
    "end": "Bava Batra 73b:3",
    "length": 1,
    "start": "Bava Batra 73b:3"
  },
  {
    "end": "Bava Batra 73b:4",
    "length": 1,
    "start": "Bava Batra 73b:4"
  },
  {
    "end": "Bava Batra 73b:5",
    "length": 1,
    "start": "Bava Batra 73b:5"
  },
  {
    "end": "Bava Batra 73b:6",
    "length": 1,
    "start": "Bava Batra 73b:6"
  },
  {
    "end": "Bava Batra 73b:7",
    "length": 1,
    "start": "Bava Batra 73b:7"
  },
  {
    "end": "Bava Batra 73b:8",
    "length": 1,
    "start": "Bava Batra 73b:8"
  },
  {
    "end": "Bava Batra 74a:6",
    "length": 9,
    "start": "Bava Batra 73b:9"
  },
  {
    "end": "Bava Batra 74a:7",
    "length": 1,
    "start": "Bava Batra 74a:7"
  },
  {
    "end": "Bava Batra 74b:1",
    "length": 2,
    "start": "Bava Batra 74a:8"
  },
  {
    "end": "Bava Batra 74b:2",
    "length": 1,
    "start": "Bava Batra 74b:2"
  },
  {
    "end": "Bava Batra 74b:3",
    "length": 1,
    "start": "Bava Batra 74b:3"
  },
  {
    "end": "Bava Batra 74b:4",
    "length": 1,
    "start": "Bava Batra 74b:4"
  },
  {
    "end": "Bava Batra 74b:5",
    "length": 1,
    "start": "Bava Batra 74b:5"
  },
  {
    "end": "Bava Batra 74b:11",
    "length": 6,
    "start": "Bava Batra 74b:6"
  },
  {
    "end": "Bava Batra 75a:3",
    "length": 5,
    "start": "Bava Batra 74b:12"
  },
  {
    "end": "Bava Batra 75b:11",
    "length": 26,
    "start": "Bava Batra 75a:4"
  },
  {
    "end": "Bava Batra 76b:7",
    "length": 19,
    "start": "Bava Batra 75b:12"
  },
  {
    "end": "Bava Batra 77b:3",
    "length": 9,
    "start": "Bava Batra 76b:8"
  },
  {
    "end": "Bava Batra 77b:4",
    "length": 1,
    "start": "Bava Batra 77b:4"
  },
  {
    "end": "Bava Batra 77b:5",
    "length": 1,
    "start": "Bava Batra 77b:5"
  },
  {
    "end": "Bava Batra 77b:6",
    "length": 1,
    "start": "Bava Batra 77b:6"
  },
  {
    "end": "Bava Batra 78a:2",
    "length": 4,
    "start": "Bava Batra 77b:7"
  },
  {
    "end": "Bava Batra 78a:3",
    "length": 1,
    "start": "Bava Batra 78a:3"
  },
  {
    "end": "Bava Batra 78b:6",
    "length": 14,
    "start": "Bava Batra 78a:4"
  },
  {
    "end": "Bava Batra 78b:8",
    "length": 2,
    "start": "Bava Batra 78b:7"
  },
  {
    "end": "Bava Batra 78b:9",
    "length": 1,
    "start": "Bava Batra 78b:9"
  },
  {
    "end": "Bava Batra 79a:3",
    "length": 10,
    "start": "Bava Batra 78b:10"
  },
  {
    "end": "Bava Batra 79b:7",
    "length": 17,
    "start": "Bava Batra 79a:4"
  },
  {
    "end": "Bava Batra 80a:1",
    "length": 1,
    "start": "Bava Batra 80a:1"
  },
  {
    "end": "Bava Batra 80a:3",
    "length": 2,
    "start": "Bava Batra 80a:2"
  },
  {
    "end": "Bava Batra 80a:5",
    "length": 2,
    "start": "Bava Batra 80a:4"
  },
  {
    "end": "Bava Batra 80b:9",
    "length": 11,
    "start": "Bava Batra 80a:6"
  },
  {
    "end": "Bava Batra 81a:1",
    "length": 10,
    "start": "Bava Batra 80b:10"
  },
  {
    "end": "Bava Batra 81a:3",
    "length": 2,
    "start": "Bava Batra 81a:2"
  },
  {
    "end": "Bava Batra 82a:2",
    "length": 17,
    "start": "Bava Batra 81a:4"
  },
  {
    "end": "Bava Batra 82a:8",
    "length": 6,
    "start": "Bava Batra 82a:3"
  },
  {
    "end": "Bava Batra 82b:12",
    "length": 13,
    "start": "Bava Batra 82a:9"
  },
  {
    "end": "Bava Batra 83a:8",
    "length": 12,
    "start": "Bava Batra 82b:13"
  },
  {
    "end": "Bava Batra 83b:4",
    "length": 8,
    "start": "Bava Batra 83a:9"
  },
  {
    "end": "Bava Batra 83b:7",
    "length": 3,
    "start": "Bava Batra 83b:5"
  },
  {
    "end": "Bava Batra 84a:4",
    "length": 5,
    "start": "Bava Batra 83b:8"
  },
  {
    "end": "Bava Batra 84a:7",
    "length": 3,
    "start": "Bava Batra 84a:5"
  },
  {
    "end": "Bava Batra 84b:4",
    "length": 5,
    "start": "Bava Batra 84a:8"
  },
  {
    "end": "Bava Batra 84b:6",
    "length": 2,
    "start": "Bava Batra 84b:5"
  },
  {
    "end": "Bava Batra 84b:13",
    "length": 7,
    "start": "Bava Batra 84b:7"
  },
  {
    "end": "Bava Batra 85b:2",
    "length": 9,
    "start": "Bava Batra 84b:14"
  },
  {
    "end": "Bava Batra 86a:4",
    "length": 12,
    "start": "Bava Batra 85b:3"
  },
  {
    "end": "Bava Batra 86b:3",
    "length": 8,
    "start": "Bava Batra 86a:5"
  },
  {
    "end": "Bava Batra 87a:4",
    "length": 8,
    "start": "Bava Batra 86b:4"
  },
  {
    "end": "Bava Batra 87a:5",
    "length": 1,
    "start": "Bava Batra 87a:5"
  },
  {
    "end": "Bava Batra 87a:7",
    "length": 2,
    "start": "Bava Batra 87a:6"
  },
  {
    "end": "Bava Batra 87a:9",
    "length": 2,
    "start": "Bava Batra 87a:8"
  },
  {
    "end": "Bava Batra 87b:4",
    "length": 5,
    "start": "Bava Batra 87a:10"
  },
  {
    "end": "Bava Batra 87b:5",
    "length": 1,
    "start": "Bava Batra 87b:5"
  },
  {
    "end": "Bava Batra 88a:11",
    "length": 15,
    "start": "Bava Batra 87b:6"
  },
  {
    "end": "Bava Batra 88b:2",
    "length": 4,
    "start": "Bava Batra 88a:12"
  },
  {
    "end": "Bava Batra 88b:4",
    "length": 2,
    "start": "Bava Batra 88b:3"
  },
  {
    "end": "Bava Batra 88b:5",
    "length": 1,
    "start": "Bava Batra 88b:5"
  },
  {
    "end": "Bava Batra 89a:1",
    "length": 8,
    "start": "Bava Batra 88b:6"
  },
  {
    "end": "Bava Batra 89a:6",
    "length": 5,
    "start": "Bava Batra 89a:2"
  },
  {
    "end": "Bava Batra 89a:10",
    "length": 4,
    "start": "Bava Batra 89a:7"
  },
  {
    "end": "Bava Batra 89a:13",
    "length": 3,
    "start": "Bava Batra 89a:11"
  },
  {
    "end": "Bava Batra 89b:3",
    "length": 6,
    "start": "Bava Batra 89a:14"
  },
  {
    "end": "Bava Batra 89b:7",
    "length": 4,
    "start": "Bava Batra 89b:4"
  },
  {
    "end": "Bava Batra 90a:4",
    "length": 8,
    "start": "Bava Batra 89b:8"
  },
  {
    "end": "Bava Batra 90b:2",
    "length": 7,
    "start": "Bava Batra 90a:5"
  },
  {
    "end": "Bava Batra 90b:9",
    "length": 7,
    "start": "Bava Batra 90b:3"
  },
  {
    "end": "Bava Batra 91a:6",
    "length": 7,
    "start": "Bava Batra 90b:10"
  },
  {
    "end": "Bava Batra 91b:18",
    "length": 29,
    "start": "Bava Batra 91a:7"
  },
  {
    "end": "Bava Batra 92a:1",
    "length": 1,
    "start": "Bava Batra 92a:1"
  },
  {
    "end": "Bava Batra 93b:3",
    "length": 31,
    "start": "Bava Batra 92a:2"
  },
  {
    "end": "Bava Batra 93b:13",
    "length": 10,
    "start": "Bava Batra 93b:4"
  },
  {
    "end": "Bava Batra 93b:14",
    "length": 1,
    "start": "Bava Batra 93b:14"
  },
  {
    "end": "Bava Batra 94a:6",
    "length": 7,
    "start": "Bava Batra 93b:15"
  },
  {
    "end": "Bava Batra 95a:7",
    "length": 28,
    "start": "Bava Batra 94a:7"
  },
  {
    "end": "Bava Batra 95b:11",
    "length": 16,
    "start": "Bava Batra 95a:8"
  },
  {
    "end": "Bava Batra 96b:2",
    "length": 16,
    "start": "Bava Batra 95b:12"
  },
  {
    "end": "Bava Batra 97a:3",
    "length": 8,
    "start": "Bava Batra 96b:3"
  },
  {
    "end": "Bava Batra 97a:11",
    "length": 8,
    "start": "Bava Batra 97a:4"
  },
  {
    "end": "Bava Batra 97b:11",
    "length": 13,
    "start": "Bava Batra 97a:12"
  },
  {
    "end": "Bava Batra 98a:1",
    "length": 2,
    "start": "Bava Batra 97b:12"
  },
  {
    "end": "Bava Batra 98a:12",
    "length": 11,
    "start": "Bava Batra 98a:2"
  },
  {
    "end": "Bava Batra 98b:1",
    "length": 2,
    "start": "Bava Batra 98a:13"
  },
  {
    "end": "Bava Batra 98b:4",
    "length": 3,
    "start": "Bava Batra 98b:2"
  },
  {
    "end": "Bava Batra 98b:6",
    "length": 2,
    "start": "Bava Batra 98b:5"
  },
  {
    "end": "Bava Batra 98b:8",
    "length": 2,
    "start": "Bava Batra 98b:7"
  },
  {
    "end": "Bava Batra 98b:10",
    "length": 2,
    "start": "Bava Batra 98b:9"
  },
  {
    "end": "Bava Batra 98b:13",
    "length": 3,
    "start": "Bava Batra 98b:11"
  },
  {
    "end": "Bava Batra 99a:7",
    "length": 9,
    "start": "Bava Batra 98b:14"
  },
  {
    "end": "Bava Batra 99a:8",
    "length": 1,
    "start": "Bava Batra 99a:8"
  },
  {
    "end": "Bava Batra 99b:1",
    "length": 2,
    "start": "Bava Batra 99a:9"
  },
  {
    "end": "Bava Batra 99b:3",
    "length": 2,
    "start": "Bava Batra 99b:2"
  },
  {
    "end": "Bava Batra 99b:7",
    "length": 4,
    "start": "Bava Batra 99b:4"
  },
  {
    "end": "Bava Batra 99b:9",
    "length": 2,
    "start": "Bava Batra 99b:8"
  },
  {
    "end": "Bava Batra 100a:9",
    "length": 11,
    "start": "Bava Batra 99b:10"
  },
  {
    "end": "Bava Batra 100a:10",
    "length": 1,
    "start": "Bava Batra 100a:10"
  },
  {
    "end": "Bava Batra 100b:1",
    "length": 2,
    "start": "Bava Batra 100a:11"
  },
  {
    "end": "Bava Batra 100b:2",
    "length": 1,
    "start": "Bava Batra 100b:2"
  },
  {
    "end": "Bava Batra 100b:3",
    "length": 1,
    "start": "Bava Batra 100b:3"
  },
  {
    "end": "Bava Batra 100b:9",
    "length": 6,
    "start": "Bava Batra 100b:4"
  },
  {
    "end": "Bava Batra 101a:5",
    "length": 6,
    "start": "Bava Batra 100b:10"
  },
  {
    "end": "Bava Batra 101b:7",
    "length": 10,
    "start": "Bava Batra 101a:6"
  },
  {
    "end": "Bava Batra 102b:8",
    "length": 15,
    "start": "Bava Batra 101b:8"
  },
  {
    "end": "Bava Batra 102b:9",
    "length": 1,
    "start": "Bava Batra 102b:9"
  },
  {
    "end": "Bava Batra 103a:8",
    "length": 9,
    "start": "Bava Batra 102b:10"
  },
  {
    "end": "Bava Batra 103b:3",
    "length": 6,
    "start": "Bava Batra 103a:9"
  },
  {
    "end": "Bava Batra 103b:5",
    "length": 2,
    "start": "Bava Batra 103b:4"
  },
  {
    "end": "Bava Batra 104a:4",
    "length": 5,
    "start": "Bava Batra 103b:6"
  },
  {
    "end": "Bava Batra 104a:8",
    "length": 4,
    "start": "Bava Batra 104a:5"
  },
  {
    "end": "Bava Batra 104b:4",
    "length": 6,
    "start": "Bava Batra 104a:9"
  },
  {
    "end": "Bava Batra 104b:7",
    "length": 3,
    "start": "Bava Batra 104b:5"
  },
  {
    "end": "Bava Batra 104b:8",
    "length": 1,
    "start": "Bava Batra 104b:8"
  },
  {
    "end": "Bava Batra 105a:1",
    "length": 2,
    "start": "Bava Batra 104b:9"
  },
  {
    "end": "Bava Batra 105b:5",
    "length": 12,
    "start": "Bava Batra 105a:2"
  },
  {
    "end": "Bava Batra 106a:1",
    "length": 1,
    "start": "Bava Batra 106a:1"
  },
  {
    "end": "Bava Batra 106b:3",
    "length": 8,
    "start": "Bava Batra 106a:2"
  },
  {
    "end": "Bava Batra 106b:5",
    "length": 2,
    "start": "Bava Batra 106b:4"
  },
  {
    "end": "Bava Batra 107a:1",
    "length": 5,
    "start": "Bava Batra 106b:6"
  },
  {
    "end": "Bava Batra 107a:6",
    "length": 5,
    "start": "Bava Batra 107a:2"
  },
  {
    "end": "Bava Batra 107b:5",
    "length": 8,
    "start": "Bava Batra 107a:7"
  },
  {
    "end": "Bava Batra 107b:6",
    "length": 1,
    "start": "Bava Batra 107b:6"
  },
  {
    "end": "Bava Batra 107b:8",
    "length": 2,
    "start": "Bava Batra 107b:7"
  },
  {
    "end": "Bava Batra 108a:2",
    "length": 3,
    "start": "Bava Batra 107b:9"
  },
  {
    "end": "Bava Batra 108a:4",
    "length": 2,
    "start": "Bava Batra 108a:3"
  },
  {
    "end": "Bava Batra 109a:7",
    "length": 14,
    "start": "Bava Batra 108a:5"
  },
  {
    "end": "Bava Batra 109b:3",
    "length": 5,
    "start": "Bava Batra 109a:8"
  },
  {
    "end": "Bava Batra 109b:10",
    "length": 7,
    "start": "Bava Batra 109b:4"
  },
  {
    "end": "Bava Batra 110a:6",
    "length": 9,
    "start": "Bava Batra 109b:11"
  },
  {
    "end": "Bava Batra 110b:8",
    "length": 10,
    "start": "Bava Batra 110a:7"
  },
  {
    "end": "Bava Batra 110b:11",
    "length": 3,
    "start": "Bava Batra 110b:9"
  },
  {
    "end": "Bava Batra 111b:7",
    "length": 20,
    "start": "Bava Batra 110b:12"
  },
  {
    "end": "Bava Batra 113a:5",
    "length": 30,
    "start": "Bava Batra 111b:8"
  },
  {
    "end": "Bava Batra 113a:8",
    "length": 3,
    "start": "Bava Batra 113a:6"
  },
  {
    "end": "Bava Batra 113b:2",
    "length": 3,
    "start": "Bava Batra 113a:9"
  },
  {
    "end": "Bava Batra 114a:1",
    "length": 4,
    "start": "Bava Batra 113b:3"
  },
  {
    "end": "Bava Batra 114b:1",
    "length": 4,
    "start": "Bava Batra 114a:2"
  },
  {
    "end": "Bava Batra 114b:3",
    "length": 2,
    "start": "Bava Batra 114b:2"
  },
  {
    "end": "Bava Batra 115a:6",
    "length": 7,
    "start": "Bava Batra 114b:4"
  },
  {
    "end": "Bava Batra 115a:8",
    "length": 2,
    "start": "Bava Batra 115a:7"
  },
  {
    "end": "Bava Batra 115b:1",
    "length": 3,
    "start": "Bava Batra 115a:9"
  },
  {
    "end": "Bava Batra 116a:3",
    "length": 8,
    "start": "Bava Batra 115b:2"
  },
  {
    "end": "Bava Batra 116a:15",
    "length": 12,
    "start": "Bava Batra 116a:4"
  },
  {
    "end": "Bava Batra 116b:3",
    "length": 4,
    "start": "Bava Batra 116a:16"
  },
  {
    "end": "Bava Batra 116b:4",
    "length": 1,
    "start": "Bava Batra 116b:4"
  },
  {
    "end": "Bava Batra 118a:5",
    "length": 15,
    "start": "Bava Batra 117a:1"
  },
  {
    "end": "Bava Batra 118b:2",
    "length": 4,
    "start": "Bava Batra 118a:6"
  },
  {
    "end": "Bava Batra 118b:7",
    "length": 5,
    "start": "Bava Batra 118b:3"
  },
  {
    "end": "Bava Batra 119a:1",
    "length": 7,
    "start": "Bava Batra 118b:8"
  },
  {
    "end": "Bava Batra 119a:3",
    "length": 2,
    "start": "Bava Batra 119a:2"
  },
  {
    "end": "Bava Batra 119b:4",
    "length": 9,
    "start": "Bava Batra 119a:4"
  },
  {
    "end": "Bava Batra 119b:8",
    "length": 4,
    "start": "Bava Batra 119b:5"
  },
  {
    "end": "Bava Batra 120a:3",
    "length": 8,
    "start": "Bava Batra 119b:9"
  },
  {
    "end": "Bava Batra 120a:5",
    "length": 2,
    "start": "Bava Batra 120a:4"
  },
  {
    "end": "Bava Batra 121a:5",
    "length": 20,
    "start": "Bava Batra 120a:6"
  },
  {
    "end": "Bava Batra 121b:5",
    "length": 9,
    "start": "Bava Batra 121a:6"
  },
  {
    "end": "Bava Batra 121b:11",
    "length": 6,
    "start": "Bava Batra 121b:6"
  },
  {
    "end": "Bava Batra 122a:8",
    "length": 9,
    "start": "Bava Batra 121b:12"
  },
  {
    "end": "Bava Batra 122b:2",
    "length": 6,
    "start": "Bava Batra 122a:9"
  },
  {
    "end": "Bava Batra 122b:3",
    "length": 1,
    "start": "Bava Batra 122b:3"
  },
  {
    "end": "Bava Batra 122b:14",
    "length": 11,
    "start": "Bava Batra 122b:4"
  },
  {
    "end": "Bava Batra 123a:10",
    "length": 11,
    "start": "Bava Batra 122b:15"
  },
  {
    "end": "Bava Batra 123a:20",
    "length": 10,
    "start": "Bava Batra 123a:11"
  },
  {
    "end": "Bava Batra 123b:1",
    "length": 2,
    "start": "Bava Batra 123a:21"
  },
  {
    "end": "Bava Batra 123b:4",
    "length": 3,
    "start": "Bava Batra 123b:2"
  },
  {
    "end": "Bava Batra 124a:1",
    "length": 9,
    "start": "Bava Batra 123b:5"
  },
  {
    "end": "Bava Batra 124a:8",
    "length": 7,
    "start": "Bava Batra 124a:2"
  },
  {
    "end": "Bava Batra 124b:6",
    "length": 7,
    "start": "Bava Batra 124a:9"
  },
  {
    "end": "Bava Batra 125b:6",
    "length": 23,
    "start": "Bava Batra 124b:7"
  },
  {
    "end": "Bava Batra 126a:1",
    "length": 2,
    "start": "Bava Batra 125b:7"
  },
  {
    "end": "Bava Batra 126a:6",
    "length": 5,
    "start": "Bava Batra 126a:2"
  },
  {
    "end": "Bava Batra 126b:3",
    "length": 7,
    "start": "Bava Batra 126a:7"
  },
  {
    "end": "Bava Batra 126b:5",
    "length": 2,
    "start": "Bava Batra 126b:4"
  },
  {
    "end": "Bava Batra 126b:8",
    "length": 3,
    "start": "Bava Batra 126b:6"
  },
  {
    "end": "Bava Batra 126b:12",
    "length": 4,
    "start": "Bava Batra 126b:9"
  },
  {
    "end": "Bava Batra 127a:12",
    "length": 14,
    "start": "Bava Batra 126b:13"
  },
  {
    "end": "Bava Batra 127b:13",
    "length": 14,
    "start": "Bava Batra 127a:13"
  },
  {
    "end": "Bava Batra 127b:17",
    "length": 4,
    "start": "Bava Batra 127b:14"
  },
  {
    "end": "Bava Batra 128a:3",
    "length": 4,
    "start": "Bava Batra 127b:18"
  },
  {
    "end": "Bava Batra 128a:4",
    "length": 1,
    "start": "Bava Batra 128a:4"
  },
  {
    "end": "Bava Batra 128a:6",
    "length": 2,
    "start": "Bava Batra 128a:5"
  },
  {
    "end": "Bava Batra 128b:1",
    "length": 6,
    "start": "Bava Batra 128a:7"
  },
  {
    "end": "Bava Batra 128b:5",
    "length": 4,
    "start": "Bava Batra 128b:2"
  },
  {
    "end": "Bava Batra 128b:6",
    "length": 1,
    "start": "Bava Batra 128b:6"
  },
  {
    "end": "Bava Batra 128b:9",
    "length": 3,
    "start": "Bava Batra 128b:7"
  },
  {
    "end": "Bava Batra 129a:2",
    "length": 4,
    "start": "Bava Batra 128b:10"
  },
  {
    "end": "Bava Batra 130a:1",
    "length": 23,
    "start": "Bava Batra 129a:3"
  },
  {
    "end": "Bava Batra 130a:2",
    "length": 1,
    "start": "Bava Batra 130a:2"
  },
  {
    "end": "Bava Batra 130a:7",
    "length": 5,
    "start": "Bava Batra 130a:3"
  },
  {
    "end": "Bava Batra 130b:7",
    "length": 11,
    "start": "Bava Batra 130a:8"
  },
  {
    "end": "Bava Batra 131a:1",
    "length": 7,
    "start": "Bava Batra 130b:8"
  },
  {
    "end": "Bava Batra 131b:4",
    "length": 16,
    "start": "Bava Batra 131a:2"
  },
  {
    "end": "Bava Batra 131b:11",
    "length": 7,
    "start": "Bava Batra 131b:5"
  },
  {
    "end": "Bava Batra 132a:10",
    "length": 10,
    "start": "Bava Batra 132a:1"
  },
  {
    "end": "Bava Batra 132b:6",
    "length": 8,
    "start": "Bava Batra 132a:11"
  },
  {
    "end": "Bava Batra 133a:2",
    "length": 5,
    "start": "Bava Batra 132b:7"
  },
  {
    "end": "Bava Batra 133b:3",
    "length": 10,
    "start": "Bava Batra 133a:3"
  },
  {
    "end": "Bava Batra 133b:4",
    "length": 1,
    "start": "Bava Batra 133b:4"
  },
  {
    "end": "Bava Batra 133b:11",
    "length": 7,
    "start": "Bava Batra 133b:5"
  },
  {
    "end": "Bava Batra 134a:5",
    "length": 7,
    "start": "Bava Batra 133b:12"
  },
  {
    "end": "Bava Batra 134a:9",
    "length": 4,
    "start": "Bava Batra 134a:6"
  },
  {
    "end": "Bava Batra 134a:12",
    "length": 3,
    "start": "Bava Batra 134a:10"
  },
  {
    "end": "Bava Batra 134b:3",
    "length": 4,
    "start": "Bava Batra 134a:13"
  },
  {
    "end": "Bava Batra 135a:6",
    "length": 18,
    "start": "Bava Batra 134b:4"
  },
  {
    "end": "Bava Batra 135b:1",
    "length": 6,
    "start": "Bava Batra 135a:7"
  },
  {
    "end": "Bava Batra 135b:3",
    "length": 2,
    "start": "Bava Batra 135b:2"
  },
  {
    "end": "Bava Batra 135b:4",
    "length": 1,
    "start": "Bava Batra 135b:4"
  },
  {
    "end": "Bava Batra 135b:6",
    "length": 2,
    "start": "Bava Batra 135b:5"
  },
  {
    "end": "Bava Batra 136a:2",
    "length": 9,
    "start": "Bava Batra 135b:7"
  },
  {
    "end": "Bava Batra 136a:5",
    "length": 3,
    "start": "Bava Batra 136a:3"
  },
  {
    "end": "Bava Batra 136a:7",
    "length": 2,
    "start": "Bava Batra 136a:6"
  },
  {
    "end": "Bava Batra 136a:14",
    "length": 7,
    "start": "Bava Batra 136a:8"
  },
  {
    "end": "Bava Batra 137a:5",
    "length": 18,
    "start": "Bava Batra 136a:15"
  },
  {
    "end": "Bava Batra 137a:13",
    "length": 8,
    "start": "Bava Batra 137a:6"
  },
  {
    "end": "Bava Batra 137b:2",
    "length": 4,
    "start": "Bava Batra 137a:14"
  },
  {
    "end": "Bava Batra 137b:5",
    "length": 3,
    "start": "Bava Batra 137b:3"
  },
  {
    "end": "Bava Batra 137b:7",
    "length": 2,
    "start": "Bava Batra 137b:6"
  },
  {
    "end": "Bava Batra 137b:9",
    "length": 2,
    "start": "Bava Batra 137b:8"
  },
  {
    "end": "Bava Batra 138a:7",
    "length": 9,
    "start": "Bava Batra 137b:10"
  },
  {
    "end": "Bava Batra 138a:9",
    "length": 2,
    "start": "Bava Batra 138a:8"
  },
  {
    "end": "Bava Batra 138b:7",
    "length": 9,
    "start": "Bava Batra 138a:10"
  },
  {
    "end": "Bava Batra 138b:12",
    "length": 5,
    "start": "Bava Batra 138b:8"
  },
  {
    "end": "Bava Batra 138b:13",
    "length": 1,
    "start": "Bava Batra 138b:13"
  },
  {
    "end": "Bava Batra 139a:2",
    "length": 3,
    "start": "Bava Batra 138b:14"
  },
  {
    "end": "Bava Batra 139a:7",
    "length": 5,
    "start": "Bava Batra 139a:3"
  },
  {
    "end": "Bava Batra 139a:10",
    "length": 3,
    "start": "Bava Batra 139a:8"
  },
  {
    "end": "Bava Batra 139a:12",
    "length": 2,
    "start": "Bava Batra 139a:11"
  },
  {
    "end": "Bava Batra 139b:6",
    "length": 15,
    "start": "Bava Batra 139a:13"
  },
  {
    "end": "Bava Batra 139b:7",
    "length": 1,
    "start": "Bava Batra 139b:7"
  },
  {
    "end": "Bava Batra 140a:1",
    "length": 4,
    "start": "Bava Batra 139b:8"
  },
  {
    "end": "Bava Batra 140a:3",
    "length": 2,
    "start": "Bava Batra 140a:2"
  },
  {
    "end": "Bava Batra 140b:2",
    "length": 6,
    "start": "Bava Batra 140a:4"
  },
  {
    "end": "Bava Batra 140b:3",
    "length": 1,
    "start": "Bava Batra 140b:3"
  },
  {
    "end": "Bava Batra 140b:6",
    "length": 3,
    "start": "Bava Batra 140b:4"
  },
  {
    "end": "Bava Batra 141a:1",
    "length": 4,
    "start": "Bava Batra 140b:7"
  },
  {
    "end": "Bava Batra 141a:7",
    "length": 6,
    "start": "Bava Batra 141a:2"
  },
  {
    "end": "Bava Batra 141b:2",
    "length": 5,
    "start": "Bava Batra 141a:8"
  },
  {
    "end": "Bava Batra 142b:5",
    "length": 23,
    "start": "Bava Batra 141b:3"
  },
  {
    "end": "Bava Batra 143a:1",
    "length": 6,
    "start": "Bava Batra 142b:6"
  },
  {
    "end": "Bava Batra 143a:9",
    "length": 8,
    "start": "Bava Batra 143a:2"
  },
  {
    "end": "Bava Batra 143b:3",
    "length": 8,
    "start": "Bava Batra 143a:10"
  },
  {
    "end": "Bava Batra 143b:7",
    "length": 4,
    "start": "Bava Batra 143b:4"
  },
  {
    "end": "Bava Batra 143b:8",
    "length": 1,
    "start": "Bava Batra 143b:8"
  },
  {
    "end": "Bava Batra 144a:1",
    "length": 3,
    "start": "Bava Batra 143b:9"
  },
  {
    "end": "Bava Batra 144a:2",
    "length": 1,
    "start": "Bava Batra 144a:2"
  },
  {
    "end": "Bava Batra 144a:4",
    "length": 2,
    "start": "Bava Batra 144a:3"
  },
  {
    "end": "Bava Batra 144a:5",
    "length": 1,
    "start": "Bava Batra 144a:5"
  },
  {
    "end": "Bava Batra 144a:9",
    "length": 4,
    "start": "Bava Batra 144a:6"
  },
  {
    "end": "Bava Batra 144b:1",
    "length": 1,
    "start": "Bava Batra 144b:1"
  },
  {
    "end": "Bava Batra 144b:5",
    "length": 4,
    "start": "Bava Batra 144b:2"
  },
  {
    "end": "Bava Batra 144b:6",
    "length": 1,
    "start": "Bava Batra 144b:6"
  },
  {
    "end": "Bava Batra 144b:7",
    "length": 1,
    "start": "Bava Batra 144b:7"
  },
  {
    "end": "Bava Batra 145a:2",
    "length": 8,
    "start": "Bava Batra 144b:8"
  },
  {
    "end": "Bava Batra 145a:14",
    "length": 12,
    "start": "Bava Batra 145a:3"
  },
  {
    "end": "Bava Batra 145b:3",
    "length": 4,
    "start": "Bava Batra 145a:15"
  },
  {
    "end": "Bava Batra 145b:7",
    "length": 4,
    "start": "Bava Batra 145b:4"
  },
  {
    "end": "Bava Batra 146a:2",
    "length": 7,
    "start": "Bava Batra 145b:8"
  },
  {
    "end": "Bava Batra 146a:3",
    "length": 1,
    "start": "Bava Batra 146a:3"
  },
  {
    "end": "Bava Batra 146a:4",
    "length": 1,
    "start": "Bava Batra 146a:4"
  },
  {
    "end": "Bava Batra 146a:11",
    "length": 7,
    "start": "Bava Batra 146a:5"
  },
  {
    "end": "Bava Batra 146b:1",
    "length": 3,
    "start": "Bava Batra 146a:12"
  },
  {
    "end": "Bava Batra 146b:2",
    "length": 1,
    "start": "Bava Batra 146b:2"
  },
  {
    "end": "Bava Batra 146b:3",
    "length": 1,
    "start": "Bava Batra 146b:3"
  },
  {
    "end": "Bava Batra 147a:3",
    "length": 7,
    "start": "Bava Batra 146b:4"
  },
  {
    "end": "Bava Batra 147a:9",
    "length": 6,
    "start": "Bava Batra 147a:4"
  },
  {
    "end": "Bava Batra 147b:1",
    "length": 8,
    "start": "Bava Batra 147a:10"
  },
  {
    "end": "Bava Batra 147b:4",
    "length": 3,
    "start": "Bava Batra 147b:2"
  },
  {
    "end": "Bava Batra 148a:2",
    "length": 4,
    "start": "Bava Batra 147b:5"
  },
  {
    "end": "Bava Batra 148b:3",
    "length": 6,
    "start": "Bava Batra 148a:3"
  },
  {
    "end": "Bava Batra 148b:5",
    "length": 2,
    "start": "Bava Batra 148b:4"
  },
  {
    "end": "Bava Batra 148b:7",
    "length": 2,
    "start": "Bava Batra 148b:6"
  },
  {
    "end": "Bava Batra 148b:12",
    "length": 5,
    "start": "Bava Batra 148b:8"
  },
  {
    "end": "Bava Batra 148b:16",
    "length": 4,
    "start": "Bava Batra 148b:13"
  },
  {
    "end": "Bava Batra 149a:1",
    "length": 3,
    "start": "Bava Batra 148b:17"
  },
  {
    "end": "Bava Batra 149a:2",
    "length": 1,
    "start": "Bava Batra 149a:2"
  },
  {
    "end": "Bava Batra 149a:6",
    "length": 4,
    "start": "Bava Batra 149a:3"
  },
  {
    "end": "Bava Batra 150a:4",
    "length": 8,
    "start": "Bava Batra 149b:1"
  },
  {
    "end": "Bava Batra 150b:1",
    "length": 6,
    "start": "Bava Batra 150a:5"
  },
  {
    "end": "Bava Batra 150b:9",
    "length": 8,
    "start": "Bava Batra 150b:2"
  },
  {
    "end": "Bava Batra 151a:3",
    "length": 7,
    "start": "Bava Batra 150b:10"
  },
  {
    "end": "Bava Batra 151a:6",
    "length": 3,
    "start": "Bava Batra 151a:4"
  },
  {
    "end": "Bava Batra 151a:9",
    "length": 3,
    "start": "Bava Batra 151a:7"
  },
  {
    "end": "Bava Batra 151a:10",
    "length": 1,
    "start": "Bava Batra 151a:10"
  },
  {
    "end": "Bava Batra 151a:11",
    "length": 1,
    "start": "Bava Batra 151a:11"
  },
  {
    "end": "Bava Batra 151b:3",
    "length": 4,
    "start": "Bava Batra 151a:12"
  },
  {
    "end": "Bava Batra 151b:12",
    "length": 9,
    "start": "Bava Batra 151b:4"
  },
  {
    "end": "Bava Batra 152b:3",
    "length": 10,
    "start": "Bava Batra 152a:1"
  },
  {
    "end": "Bava Batra 153a:2",
    "length": 7,
    "start": "Bava Batra 152b:4"
  },
  {
    "end": "Bava Batra 153a:10",
    "length": 8,
    "start": "Bava Batra 153a:3"
  },
  {
    "end": "Bava Batra 153a:11",
    "length": 1,
    "start": "Bava Batra 153a:11"
  },
  {
    "end": "Bava Batra 153b:6",
    "length": 7,
    "start": "Bava Batra 153a:12"
  },
  {
    "end": "Bava Batra 155a:2",
    "length": 27,
    "start": "Bava Batra 153b:7"
  },
  {
    "end": "Bava Batra 155b:3",
    "length": 5,
    "start": "Bava Batra 155a:3"
  },
  {
    "end": "Bava Batra 155b:5",
    "length": 2,
    "start": "Bava Batra 155b:4"
  },
  {
    "end": "Bava Batra 155b:7",
    "length": 2,
    "start": "Bava Batra 155b:6"
  },
  {
    "end": "Bava Batra 155b:9",
    "length": 2,
    "start": "Bava Batra 155b:8"
  },
  {
    "end": "Bava Batra 155b:11",
    "length": 2,
    "start": "Bava Batra 155b:10"
  },
  {
    "end": "Bava Batra 156a:2",
    "length": 3,
    "start": "Bava Batra 155b:12"
  },
  {
    "end": "Bava Batra 156a:9",
    "length": 7,
    "start": "Bava Batra 156a:3"
  },
  {
    "end": "Bava Batra 156b:1",
    "length": 2,
    "start": "Bava Batra 156a:10"
  },
  {
    "end": "Bava Batra 156b:3",
    "length": 2,
    "start": "Bava Batra 156b:2"
  },
  {
    "end": "Bava Batra 156b:6",
    "length": 3,
    "start": "Bava Batra 156b:4"
  },
  {
    "end": "Bava Batra 156b:8",
    "length": 2,
    "start": "Bava Batra 156b:7"
  },
  {
    "end": "Bava Batra 157a:2",
    "length": 4,
    "start": "Bava Batra 156b:9"
  },
  {
    "end": "Bava Batra 157a:4",
    "length": 2,
    "start": "Bava Batra 157a:3"
  },
  {
    "end": "Bava Batra 157b:7",
    "length": 14,
    "start": "Bava Batra 157a:5"
  },
  {
    "end": "Bava Batra 157b:11",
    "length": 4,
    "start": "Bava Batra 157b:8"
  },
  {
    "end": "Bava Batra 158a:2",
    "length": 2,
    "start": "Bava Batra 158a:1"
  },
  {
    "end": "Bava Batra 158b:2",
    "length": 2,
    "start": "Bava Batra 158b:1"
  },
  {
    "end": "Bava Batra 158b:3",
    "length": 1,
    "start": "Bava Batra 158b:3"
  },
  {
    "end": "Bava Batra 158b:5",
    "length": 2,
    "start": "Bava Batra 158b:4"
  },
  {
    "end": "Bava Batra 158b:6",
    "length": 1,
    "start": "Bava Batra 158b:6"
  },
  {
    "end": "Bava Batra 159b:4",
    "length": 17,
    "start": "Bava Batra 158b:7"
  },
  {
    "end": "Bava Batra 159b:9",
    "length": 5,
    "start": "Bava Batra 159b:5"
  },
  {
    "end": "Bava Batra 159b:16",
    "length": 7,
    "start": "Bava Batra 159b:10"
  },
  {
    "end": "Bava Batra 160a:3",
    "length": 3,
    "start": "Bava Batra 160a:1"
  },
  {
    "end": "Bava Batra 160b:11",
    "length": 12,
    "start": "Bava Batra 160a:4"
  },
  {
    "end": "Bava Batra 161a:2",
    "length": 9,
    "start": "Bava Batra 160b:12"
  },
  {
    "end": "Bava Batra 161b:4",
    "length": 11,
    "start": "Bava Batra 161a:3"
  },
  {
    "end": "Bava Batra 162b:6",
    "length": 10,
    "start": "Bava Batra 161b:5"
  },
  {
    "end": "Bava Batra 163a:6",
    "length": 7,
    "start": "Bava Batra 162b:7"
  },
  {
    "end": "Bava Batra 163b:7",
    "length": 12,
    "start": "Bava Batra 163a:7"
  },
  {
    "end": "Bava Batra 164a:11",
    "length": 12,
    "start": "Bava Batra 163b:8"
  },
  {
    "end": "Bava Batra 164b:6",
    "length": 7,
    "start": "Bava Batra 164a:12"
  },
  {
    "end": "Bava Batra 164b:12",
    "length": 6,
    "start": "Bava Batra 164b:7"
  },
  {
    "end": "Bava Batra 165a:2",
    "length": 6,
    "start": "Bava Batra 164b:13"
  },
  {
    "end": "Bava Batra 165a:9",
    "length": 7,
    "start": "Bava Batra 165a:3"
  },
  {
    "end": "Bava Batra 165b:15",
    "length": 19,
    "start": "Bava Batra 165a:10"
  },
  {
    "end": "Bava Batra 165b:18",
    "length": 3,
    "start": "Bava Batra 165b:16"
  },
  {
    "end": "Bava Batra 166b:1",
    "length": 12,
    "start": "Bava Batra 165b:19"
  },
  {
    "end": "Bava Batra 166b:7",
    "length": 6,
    "start": "Bava Batra 166b:2"
  },
  {
    "end": "Bava Batra 167a:1",
    "length": 2,
    "start": "Bava Batra 166b:8"
  },
  {
    "end": "Bava Batra 167a:3",
    "length": 2,
    "start": "Bava Batra 167a:2"
  },
  {
    "end": "Bava Batra 167a:7",
    "length": 4,
    "start": "Bava Batra 167a:4"
  },
  {
    "end": "Bava Batra 167b:5",
    "length": 6,
    "start": "Bava Batra 167a:8"
  },
  {
    "end": "Bava Batra 167b:14",
    "length": 9,
    "start": "Bava Batra 167b:6"
  },
  {
    "end": "Bava Batra 168a:3",
    "length": 5,
    "start": "Bava Batra 167b:15"
  },
  {
    "end": "Bava Batra 168a:4",
    "length": 1,
    "start": "Bava Batra 168a:4"
  },
  {
    "end": "Bava Batra 168a:5",
    "length": 1,
    "start": "Bava Batra 168a:5"
  },
  {
    "end": "Bava Batra 168a:6",
    "length": 1,
    "start": "Bava Batra 168a:6"
  },
  {
    "end": "Bava Batra 168a:7",
    "length": 1,
    "start": "Bava Batra 168a:7"
  },
  {
    "end": "Bava Batra 168a:8",
    "length": 1,
    "start": "Bava Batra 168a:8"
  },
  {
    "end": "Bava Batra 168a:9",
    "length": 1,
    "start": "Bava Batra 168a:9"
  },
  {
    "end": "Bava Batra 168a:12",
    "length": 3,
    "start": "Bava Batra 168a:10"
  },
  {
    "end": "Bava Batra 168a:13",
    "length": 1,
    "start": "Bava Batra 168a:13"
  },
  {
    "end": "Bava Batra 168a:16",
    "length": 3,
    "start": "Bava Batra 168a:14"
  },
  {
    "end": "Bava Batra 168b:1",
    "length": 2,
    "start": "Bava Batra 168a:17"
  },
  {
    "end": "Bava Batra 168b:5",
    "length": 4,
    "start": "Bava Batra 168b:2"
  },
  {
    "end": "Bava Batra 168b:9",
    "length": 4,
    "start": "Bava Batra 168b:6"
  },
  {
    "end": "Bava Batra 169a:1",
    "length": 2,
    "start": "Bava Batra 168b:10"
  },
  {
    "end": "Bava Batra 169a:8",
    "length": 7,
    "start": "Bava Batra 169a:2"
  },
  {
    "end": "Bava Batra 169b:6",
    "length": 8,
    "start": "Bava Batra 169a:9"
  },
  {
    "end": "Bava Batra 169b:11",
    "length": 5,
    "start": "Bava Batra 169b:7"
  },
  {
    "end": "Bava Batra 170b:1",
    "length": 24,
    "start": "Bava Batra 169b:12"
  },
  {
    "end": "Bava Batra 170b:2",
    "length": 1,
    "start": "Bava Batra 170b:2"
  },
  {
    "end": "Bava Batra 171a:7",
    "length": 10,
    "start": "Bava Batra 170b:3"
  },
  {
    "end": "Bava Batra 171b:3",
    "length": 6,
    "start": "Bava Batra 171a:8"
  },
  {
    "end": "Bava Batra 171b:10",
    "length": 7,
    "start": "Bava Batra 171b:4"
  },
  {
    "end": "Bava Batra 172a:3",
    "length": 10,
    "start": "Bava Batra 171b:11"
  },
  {
    "end": "Bava Batra 172a:9",
    "length": 6,
    "start": "Bava Batra 172a:4"
  },
  {
    "end": "Bava Batra 172a:13",
    "length": 4,
    "start": "Bava Batra 172a:10"
  },
  {
    "end": "Bava Batra 173a:9",
    "length": 18,
    "start": "Bava Batra 172a:14"
  },
  {
    "end": "Bava Batra 173a:13",
    "length": 4,
    "start": "Bava Batra 173a:10"
  },
  {
    "end": "Bava Batra 173a:17",
    "length": 4,
    "start": "Bava Batra 173a:14"
  },
  {
    "end": "Bava Batra 173a:18",
    "length": 1,
    "start": "Bava Batra 173a:18"
  },
  {
    "end": "Bava Batra 173a:19",
    "length": 1,
    "start": "Bava Batra 173a:19"
  },
  {
    "end": "Bava Batra 173a:22",
    "length": 3,
    "start": "Bava Batra 173a:20"
  },
  {
    "end": "Bava Batra 173b:2",
    "length": 3,
    "start": "Bava Batra 173a:23"
  },
  {
    "end": "Bava Batra 173b:8",
    "length": 6,
    "start": "Bava Batra 173b:3"
  },
  {
    "end": "Bava Batra 173b:12",
    "length": 4,
    "start": "Bava Batra 173b:9"
  },
  {
    "end": "Bava Batra 173b:15",
    "length": 3,
    "start": "Bava Batra 173b:13"
  },
  {
    "end": "Bava Batra 174a:2",
    "length": 5,
    "start": "Bava Batra 173b:16"
  },
  {
    "end": "Bava Batra 174a:10",
    "length": 8,
    "start": "Bava Batra 174a:3"
  },
  {
    "end": "Bava Batra 174a:12",
    "length": 2,
    "start": "Bava Batra 174a:11"
  },
  {
    "end": "Bava Batra 174b:8",
    "length": 11,
    "start": "Bava Batra 174a:13"
  },
  {
    "end": "Bava Batra 174b:18",
    "length": 10,
    "start": "Bava Batra 174b:9"
  },
  {
    "end": "Bava Batra 175a:4",
    "length": 6,
    "start": "Bava Batra 174b:19"
  },
  {
    "end": "Bava Batra 175a:7",
    "length": 3,
    "start": "Bava Batra 175a:5"
  },
  {
    "end": "Bava Batra 175a:9",
    "length": 2,
    "start": "Bava Batra 175a:8"
  },
  {
    "end": "Bava Batra 175b:5",
    "length": 6,
    "start": "Bava Batra 175a:10"
  },
  {
    "end": "Bava Batra 176a:1",
    "length": 14,
    "start": "Bava Batra 175b:6"
  },
  {
    "end": "Bava Batra 176a:5",
    "length": 4,
    "start": "Bava Batra 176a:2"
  },
  {
    "end": "Bava Batra 176a:13",
    "length": 8,
    "start": "Bava Batra 176a:6"
  },
  {
    "end": "Bava Batra 176b:3",
    "length": 7,
    "start": "Bava Batra 176a:14"
  }
]
